DSD Lab/Week 1/q1_b.v
module q1_b(x1,x2,x3,f);
input x1,x2,x3;
output f;
assign f = (x1 & x2) | (~x2 & x3);
endmodule

DSD Lab/Week 1/q1_b_tb.v
`timescale 1ns/1ns
`include "q1_b.v"
module q1_b_tb;
reg x1,x2,x3;
wire f;
q1_b uut(x1,x2,x3,f);
initial
begin
$dumpfile("q1_b_tb.vcd");
$dumpvars(0,q1_b_tb);
x1=0;x2=0;x3=0;#20;
x1=0;x2=0;x3=1;#20;
x1=0;x2=1;x3=0;#20;
x1=0;x2=1;x3=1;#20;
x1=1;x2=0;x3=0;#20;
x1=1;x2=0;x3=1;#20;
x1=1;x2=1;x3=0;#20;
x1=1;x2=1;x3=1;#20;
$display("Test Complete");
end
endmodule

DSD Lab/Week 1/q1_b_tb.vcd
$date
	Thu Aug  3 11:00:29 2023
$end
$version
	Icarus Verilog
$end
$timescale
	1ns
$end
$scope module q1_b_tb $end
$var wire 1 ! f $end
$var reg 1 " x1 $end
$var reg 1 # x2 $end
$var reg 1 $ x3 $end
$scope module uut $end
$var wire 1 ! f $end
$var wire 1 " x1 $end
$var wire 1 # x2 $end
$var wire 1 $ x3 $end
$upscope $end
$upscope $end
$enddefinitions $end
#0
$dumpvars
0$
0#
0"
0!
$end
#20
1!
1$
#40
0!
0$
1#
#60
1$
#80
0$
0#
1"
#100
1!
1$
#120
0$
1#
#140
1$
